QuantyLF/QuantyLF.py
QuantyLF/__init__.py
QuantyLF/cases/D3h_3d.lua
QuantyLF/cases/D3h_3d.txt
QuantyLF/cases/D4h_3d.lua
QuantyLF/cases/D4h_3d.txt
QuantyLF/cases/Oh_3d.lua
QuantyLF/cases/Oh_3d.txt
QuantyLF/cases/Td_3d.lua
QuantyLF/cases/Td_3d.txt
QuantyLF/cases/utils/slater_integrals.lua
QuantyLF/cases/utils/slater_integrals.py
quantylf-0.1.22.dist-info/licenses/LICENSE
quantylf-0.1.22.dist-info/METADATA
quantylf-0.1.22.dist-info/WHEEL
quantylf-0.1.22.dist-info/top_level.txt
quantylf-0.1.22.dist-info/RECORD
