Metadata-Version: 2.4
Name: QuantyLF
Version: 0.1.22
Summary: QuantyLF is a libary to help manage Liegand Field simulations in Quanty.
Home-page: https://github.com/CMM02/XPlotLib
Author: Carl Magnus Meier
Author-email: magnus.meier@outook.de
Classifier: Programming Language :: Python :: 3
Classifier: License :: OSI Approved :: MIT License
Classifier: Operating System :: OS Independent
Requires-Python: >=3.10
License-File: LICENSE
Requires-Dist: numpy
Requires-Dist: matplotlib
Requires-Dist: scipy
Requires-Dist: lmfit
Provides-Extra: dev
Requires-Dist: pytest; extra == "dev"
Requires-Dist: pytest-cov; extra == "dev"
Requires-Dist: methylcheck; extra == "dev"
Dynamic: license-file
